roboto/__init__.py
roboto/api_version.py
roboto/association.py
roboto/collection_utils.py
roboto/config.py
roboto/env.py
roboto/logging.py
roboto/paths.py
roboto/principal.py
roboto/progress.py
roboto/py.typed
roboto/regionalization.py
roboto/roboto_search.py
roboto/sentinels.py
roboto/time.py
roboto/types.py
roboto/updates.py
roboto/waiters.py
roboto/warnings.py
roboto/action_runtime/__init__.py
roboto/action_runtime/exceptions.py
roboto/action_runtime/exit_codes.py
roboto/action_runtime/file_changeset.py
roboto/action_runtime/invocation_context.py
roboto/action_runtime/prepare.py
roboto/action_runtime/action_input/__init__.py
roboto/action_runtime/action_input/action_input.py
roboto/action_runtime/action_input/file_resolver.py
roboto/action_runtime/action_input/input_resolver.py
roboto/action_runtime/action_input/topic_resolver.py
roboto/ai/__init__.py
roboto/ai/record.py
roboto/ai/summary.py
roboto/ai/chat/__init__.py
roboto/ai/chat/chat.py
roboto/ai/chat/event.py
roboto/ai/chat/record.py
roboto/ai/core/__init__.py
roboto/ai/core/context.py
roboto/analytics/__init__.py
roboto/analytics/signal_similarity/__init__.py
roboto/analytics/signal_similarity/match.py
roboto/analytics/signal_similarity/signal_similarity.py
roboto/auth/__init__.py
roboto/auth/fga.py
roboto/auth/permissions.py
roboto/auth/scope.py
roboto/cli/__init__.py
roboto/cli/argparse.py
roboto/cli/config.py
roboto/cli/context.py
roboto/cli/devices.py
roboto/cli/entry.py
roboto/cli/terminal.py
roboto/cli/validation.py
roboto/cli/actions/__init__.py
roboto/cli/actions/commands.py
roboto/cli/actions/create.py
roboto/cli/actions/delete.py
roboto/cli/actions/init.py
roboto/cli/actions/list_invocations.py
roboto/cli/actions/search.py
roboto/cli/actions/show.py
roboto/cli/actions/update.py
roboto/cli/actions/invoke/__init__.py
roboto/cli/actions/invoke/action_resolution.py
roboto/cli/actions/invoke/cli_args.py
roboto/cli/actions/invoke/docker_action_runner.py
roboto/cli/actions/invoke/input_parsing.py
roboto-0.35.2.dist-info/licenses/LICENSE
roboto-0.35.2.dist-info/METADATA
roboto-0.35.2.dist-info/WHEEL
roboto-0.35.2.dist-info/entry_points.txt
roboto-0.35.2.dist-info/top_level.txt
roboto-0.35.2.dist-info/RECORD
