Metadata-Version: 2.4
Name: roboto
Version: 0.35.2
Summary: Official Python toolkit for roboto.ai
Maintainer-email: Roboto AI <info@roboto.ai>
License: Mozilla Public License Version 2.0
Project-URL: Documentation, https://docs.roboto.ai
Project-URL: Homepage, https://www.roboto.ai
Project-URL: Issues, https://github.com/roboto-ai/roboto-python-sdk/issues
Project-URL: Repository, https://github.com/roboto-ai/roboto-python-sdk.git
Requires-Python: <4,>=3.9
License-File: LICENSE
Requires-Dist: boto3>=1.26
Requires-Dist: botocore>=1.29
Requires-Dist: cookiecutter>=2.5.0
Requires-Dist: cron-converter>=1.2.1
Requires-Dist: exceptiongroup>=1.0; python_version < "3.11"
Requires-Dist: filelock~=3.15
Requires-Dist: mcap>=1.3.0
Requires-Dist: mcap-ros1-support>=0.7.1
Requires-Dist: mcap-ros2-support>=0.5.3
Requires-Dist: packaging>=24.0
Requires-Dist: pathspec>=0.11
Requires-Dist: platformdirs>=4.0
Requires-Dist: pydantic>=2.5
Requires-Dist: pydantic-core>=2.14
Requires-Dist: pydantic-settings>=2.1
Requires-Dist: rich>=14.2
Requires-Dist: tenacity>=8.2
Requires-Dist: tqdm>=4.65
Requires-Dist: typing-extensions>=4.8; python_version < "3.10"
Provides-Extra: analytics
Requires-Dist: fsspec[http]>=2025.5.1; extra == "analytics"
Requires-Dist: numpy>=1.19; extra == "analytics"
Requires-Dist: pandas>=2.0; extra == "analytics"
Requires-Dist: pyarrow>=20.0.0; extra == "analytics"
Requires-Dist: stumpy>=1.13; extra == "analytics"
Provides-Extra: ingestion
Requires-Dist: pandas>=2.0; extra == "ingestion"
Requires-Dist: pyarrow>=20.0.0; extra == "ingestion"
Provides-Extra: examples
Requires-Dist: ipython~=8.28; extra == "examples"
Requires-Dist: jupyter~=1.1; extra == "examples"
Requires-Dist: matplotlib~=3.9; extra == "examples"
Requires-Dist: pillow~=10.4; extra == "examples"
Dynamic: license-file
